{
  "name": "Jigsaw Shark",
  "type": "npc",
  "img": "systems/pf2e/icons/default-icons/npc.svg",
  "data": {
    "attributes": {
      "hp": {
        "value": 20,
        "temp": 0,
        "details": "",
        "max": 20
      },
      "perception": {
        "value": 7
      },
      "initiative": {
        "ability": "perception"
      },
      "speed": {
        "value": "30",
        "otherSpeeds": [],
        "details": ""
      },
      "ac": {
        "value": 16,
        "details": ""
      },
      "allSaves": {
        "value": ""
      }
    },
    "details": {
      "alignment": {
        "value": "N"
      },
      "level": {
        "value": 1
      },
      "source": {
        "value": "Pathfinder Society Scenario 2-06: The Crashing Wave",
        "author": ""
      },
      "creatureType": "",
      "blurb": "",
      "publicNotes": "",
      "privateNotes": ""
    },
    "traits": {
      "senses": {
        "value": "blood scent, scent (imprecise) 100 feet"
      },
      "traits": {
        "value": [
          "animal",
          "aquatic"
        ],
        "custom": ""
      },
      "languages": {
        "value": [],
        "selected": [],
        "custom": ""
      },
      "di": {
        "value": [],
        "custom": ""
      },
      "dr": [],
      "dv": [],
      "rarity": "uncommon",
      "size": {
        "value": "lg"
      },
      "ci": []
    },
    "resources": {},
    "schema": {
      "version": 0.75,
      "lastMigration": null
    },
    "abilities": {
      "str": {
        "mod": 3
      },
      "dex": {
        "mod": 1
      },
      "con": {
        "mod": 4
      },
      "int": {
        "mod": -4
      },
      "wis": {
        "mod": 0
      },
      "cha": {
        "mod": -4
      }
    },
    "saves": {
      "fortitude": {
        "value": 8,
        "saveDetail": ""
      },
      "reflex": {
        "value": 6,
        "saveDetail": ""
      },
      "will": {
        "value": 5,
        "saveDetail": ""
      }
    }
  },
  "token": {
    "disposition": -1,
    "height": 2,
    "img": "systems/pf2e/icons/default-icons/npc.svg",
    "name": "Razortoothed Shark",
    "width": 2,
    "displayName": 20,
    "actorLink": false,
    "scale": 1,
    "mirrorX": false,
    "mirrorY": false,
    "lockRotation": false,
    "rotation": 0,
    "alpha": 1,
    "vision": false,
    "dimSight": 0,
    "brightSight": 0,
    "sightAngle": 0,
    "light": {
      "alpha": 0.5,
      "angle": 0,
      "bright": 0,
      "coloration": 1,
      "dim": 0,
      "gradual": true,
      "luminosity": 0.5,
      "saturation": 0,
      "contrast": 0,
      "shadows": 0,
      "animation": {
        "speed": 5,
        "intensity": 5,
        "reverse": false
      },
      "darkness": {
        "min": 0,
        "max": 1
      }
    },
    "displayBars": 20,
    "bar1": {
      "attribute": "attributes.hp"
    },
    "bar2": {
      "attribute": null
    },
    "flags": {
      "pf2e": {
        "linkToActorSize": true
      }
    },
    "randomImg": false
  },
  "items": [
    {
      "_id": "Nom1Cs7QXbb5Yl5b",
      "data": {
        "description": {
          "value": ""
        },
        "source": {
          "value": ""
        },
        "traits": {
          "value": [],
          "rarity": "common",
          "custom": ""
        },
        "rules": [],
        "slug": null,
        "schema": {
          "version": 0.75,
          "lastMigration": null
        },
        "weaponType": {
          "value": "melee"
        },
        "attack": {
          "value": ""
        },
        "damageRolls": {
          "pi7287x59mfbgvol2kk9mv": {
            "damage": "1d6+3",
            "damageType": "piercing"
          }
        },
        "bonus": {
          "value": 9
        },
        "attackEffects": {
          "value": []
        }
      },
      "flags": {},
      "img": "systems/pf2e/icons/default-icons/melee.svg",
      "name": "Jaws",
      "sort": 100000,
      "type": "melee",
      "effects": [],
      "folder": null,
      "permission": {
        "default": 0
      }
    },
    {
      "_id": "UTQLyZ7H8eYOM5p5",
      "data": {
        "description": {
          "value": "<p>The shark can smell blood in the water from up to 1 mile away.</p>"
        },
        "source": {
          "value": ""
        },
        "traits": {
          "value": [],
          "rarity": "common",
          "custom": ""
        },
        "rules": [],
        "slug": null,
        "schema": {
          "version": 0.75,
          "lastMigration": null
        },
        "actionType": {
          "value": "passive"
        },
        "actionCategory": {
          "value": "interaction"
        },
        "actions": {
          "value": null
        },
        "requirements": {
          "value": ""
        },
        "trigger": {
          "value": ""
        },
        "deathNote": false,
        "weapon": {
          "value": ""
        }
      },
      "flags": {},
      "img": "systems/pf2e/icons/actions/Passive.webp",
      "name": "Blood Scent 1 mile",
      "sort": 200000,
      "type": "action",
      "effects": [],
      "folder": null,
      "permission": {
        "default": 0
      }
    },
    {
      "_id": "IxNfNOqMbA8w7wot",
      "data": {
        "description": {
          "value": "<p>@Localize[PF2E.NPC.Abilities.Glossary.Scent]</p>"
        },
        "source": {
          "value": ""
        },
        "traits": {
          "value": [],
          "rarity": "common",
          "custom": ""
        },
        "rules": [],
        "slug": "scent",
        "schema": {
          "version": 0.75,
          "lastMigration": null
        },
        "actionType": {
          "value": "passive"
        },
        "actionCategory": {
          "value": "interaction"
        },
        "actions": {
          "value": null
        },
        "requirements": {
          "value": ""
        },
        "trigger": {
          "value": ""
        },
        "deathNote": false,
        "weapon": {
          "value": ""
        }
      },
      "flags": {
        "core": {
          "sourceId": "Compendium.pf2e.bestiary-ability-glossary-srd.rqfnQ5VHT5hxm25r"
        }
      },
      "img": "systems/pf2e/icons/actions/Passive.webp",
      "name": "Scent (Imprecise) 100 feet",
      "sort": 500000,
      "type": "action",
      "effects": [],
      "folder": null,
      "permission": {
        "default": 0
      }
    },
    {
      "_id": "69MZMQoPzOTaa0gd",
      "data": {
        "description": {
          "value": "<p>The shark Swims up to its swim Speed, then Leaps vertically out of the water up to 15 feet high, making a Strike against a creature at any point during the jump (this lets it attack a creature within 20 feet of the water's surface). After the Strike, the shark splashes back down into the water.</p>"
        },
        "source": {
          "value": ""
        },
        "traits": {
          "value": [],
          "rarity": "common",
          "custom": ""
        },
        "rules": [],
        "slug": null,
        "schema": {
          "version": 0.75,
          "lastMigration": null
        },
        "actionType": {
          "value": "action"
        },
        "actionCategory": {
          "value": "offensive"
        },
        "actions": {
          "value": 2
        },
        "requirements": {
          "value": ""
        },
        "trigger": {
          "value": ""
        },
        "deathNote": false,
        "weapon": {
          "value": ""
        }
      },
      "flags": {},
      "img": "systems/pf2e/icons/actions/TwoActions.webp",
      "name": "Breach",
      "sort": 400000,
      "type": "action",
      "effects": [],
      "folder": null,
      "permission": {
        "default": 0
      }
    },
    {
      "_id": "wYdsS6W2PmhhzlKp",
      "data": {
        "description": {
          "value": ""
        },
        "source": {
          "value": ""
        },
        "traits": {
          "value": [],
          "rarity": "common",
          "custom": ""
        },
        "rules": [],
        "slug": null,
        "schema": {
          "version": 0.75,
          "lastMigration": null
        },
        "mod": {
          "value": 9
        },
        "proficient": {
          "value": 0
        }
      },
      "flags": {},
      "img": "systems/pf2e/icons/default-icons/lore.svg",
      "name": "Athletics",
      "sort": 500000,
      "type": "lore",
      "effects": [],
      "folder": null,
      "permission": {
        "default": 0
      }
    },
    {
      "_id": "z1V7x7NtG21SRrMN",
      "data": {
        "description": {
          "value": ""
        },
        "source": {
          "value": ""
        },
        "traits": {
          "value": [],
          "rarity": "common",
          "custom": ""
        },
        "rules": [],
        "slug": null,
        "schema": {
          "version": 0.75,
          "lastMigration": null
        },
        "mod": {
          "value": 6
        },
        "proficient": {
          "value": 0
        }
      },
      "flags": {},
      "img": "systems/pf2e/icons/default-icons/lore.svg",
      "name": "Stealth",
      "sort": 600000,
      "type": "lore",
      "effects": [],
      "folder": null,
      "permission": {
        "default": 0
      }
    },
    {
      "_id": "sQpP9xPCcYPTvBui",
      "data": {
        "description": {
          "value": ""
        },
        "source": {
          "value": ""
        },
        "traits": {
          "value": [],
          "rarity": "common",
          "custom": ""
        },
        "rules": [],
        "slug": null,
        "schema": {
          "version": 0.75,
          "lastMigration": null
        },
        "mod": {
          "value": 5
        },
        "proficient": {
          "value": 0
        }
      },
      "flags": {},
      "img": "systems/pf2e/icons/default-icons/lore.svg",
      "name": "Survival",
      "sort": 700000,
      "type": "lore",
      "effects": [],
      "folder": null,
      "permission": {
        "default": 0
      }
    }
  ],
  "effects": [],
  "flags": {
    "core": {
      "sourceId": "Compendium.pf2e.pfs-season-2-bestiary.83k9JooGu3wbCJKa"
    },
    "exportSource": {
      "world": "curse-of-the-crimson-throne",
      "system": "pf2e",
      "coreVersion": "9.269",
      "systemVersion": "3.10.3.11650"
    }
  }
}